resultsdb/__init__.py
resultsdb/resultsdb.py
resultsdb/data/contests.json
resultsdb/data/results.json
resultsdb/data/slates.json
resultsdbrg-0.1.dist-info/LICENSE
resultsdbrg-0.1.dist-info/METADATA
resultsdbrg-0.1.dist-info/WHEEL
resultsdbrg-0.1.dist-info/top_level.txt
resultsdbrg-0.1.dist-info/RECORD
